crates/__init__.py
crates/common/__init__.py
crates/common/output.py
crates/common/s3.py
crates/common/stdout.py
crates/service/__init__.py
crates/service/fatherhood.py
crates/service/github.py
crates/service/oura.py
crates/service/reddit.py
crates/service/slack.py
crates/service/twitter.py
crates/service/youtube.py
cargo_crates-0.0.1.dist-info/LICENSE
cargo_crates-0.0.1.dist-info/METADATA
cargo_crates-0.0.1.dist-info/WHEEL
cargo_crates-0.0.1.dist-info/top_level.txt
cargo_crates-0.0.1.dist-info/RECORD
