Metadata-Version: 2.1
Name: cargo-crates
Version: 0.0.1
Summary: An easy way to build data extractors in Docker.
Home-page: https://github.com/dacort/cargo-crates
Author: Damon P. Cortesi
Author-email: cargocrates@dcortesi.com
License: UNKNOWN
Project-URL: Bug Tracker, https://github.com/dacort/cargo-crates/issues
Platform: UNKNOWN
Classifier: Programming Language :: Python :: 3
Classifier: License :: OSI Approved :: MIT License
Classifier: Operating System :: OS Independent
Requires-Python: >=3.8
License-File: LICENSE
Requires-Dist: TwitterAPI (==2.6.6)
Requires-Dist: requests (==2.25.1)
